Metadata-Version: 2.0
Name: odoo8-addon-account-balance-reporting
Version: 8.0.1.3.0
Summary: Account balance reporting engine
Home-page: http://www.pexego.es
Author: Pexego, AvanzOSC, Tecnativa, Odoo Community Association (OCA)
Author-email: support@odoo-community.org
License: AGPL-3
Platform: UNKNOWN
Classifier: Programming Language :: Python :: 2.7
Classifier: Framework :: Odoo
Classifier: License :: OSI Approved :: GNU Affero General Public License v3
Requires-Dist: odoo (<9.0a,>=8.0a)
